Nightanday_first_package/__init__.py
Nightanday_first_package/cli.py
Nigthanday_first_package-1.0.2.dist-info/METADATA
Nigthanday_first_package-1.0.2.dist-info/WHEEL
Nigthanday_first_package-1.0.2.dist-info/entry_points.txt
Nigthanday_first_package-1.0.2.dist-info/top_level.txt
Nigthanday_first_package-1.0.2.dist-info/RECORD
