Metadata-Version: 2.2
Name: Nigthanday_first_package
Version: 1.0.2
Summary: A simple CLI package but an amazing one.
Requires-Dist: click==8.1.3
